{"inkVersion":20,"root":[["ev","str","^???","/str",{"x()":"name","exArgs":1},"out","/ev","\n","ev","str","^DailyLife","/str",2.0,{"x()":"bgm","exArgs":2},"out","/ev","\n","ev","str","^Apartment","/str",{"x()":"bg","exArgs":1},"out","/ev","\n","ev",3.0,{"x()":"fin","exArgs":1},"out","/ev","\n","^This is a test script.","\n","^Everything that's being said in the script will show up here!","\n","^Dialogue line 3...","\n","^Dialogue line 4...","\n","^Dialogue line 5...","\n","^Dialogue line 6...","\n","^Dialogue line 7...","\n","end",["done",{"#f":5,"#n":"g-0"}],null],"done",{"#f":1}],"listDefs":{}}